setup.py
cliprint/__init__.py
cliprint/cli.py
cliprint/color.py
cliprint.egg-info/PKG-INFO
cliprint.egg-info/SOURCES.txt
cliprint.egg-info/dependency_links.txt
cliprint.egg-info/entry_points.txt
cliprint.egg-info/not-zip-safe
cliprint.egg-info/top_level.txt