Metadata-Version: 1.1
Name: cliprint
Version: 0.2.0
Summary: A lightweight library of python printing functions.
Home-page: http://github.com/finnmglas/cliprint
Author: Finn M Glas
Author-email: finn@finnmglas.com
License: MIT
Platform: UNKNOWN
Classifier: Development Status :: 3 - Alpha
Classifier: License :: OSI Approved :: MIT License
Classifier: Programming Language :: Python :: 3
